{
  "name": "mountain_clans",
  "title": {
    "ru": "Горные кланы",
    "en": "Mountain clans"
  },
  "description": {
    "ru": "Народ гномов, созданный Вотаном, населяет снежные горы Невендаара и искушён в горном ремесле.",
    "en": "Race of gnomes, created by Wotan, lives in the snowy mountains of Nevendaar and is experienced in the mining craft."
  },
  "units": [
    "gnome"
  ],
  "leaders": [
    "guardian"
  ],
  "spells": [
    "ice_shield"
  ],
  "buildings": {
    "basic": [
      "thief_guild",
      "magic_guild",
      "temple"
    ],
    "melee": [
      "brewery"
    ]
  }
}
